{
    "Birdsnap": {
        "accuracy_top1": 0.42502951593860683,
        "accuracy_top5": 0.8736717827626919,
        "num_classes": 15,
        "num_images": 847,
        "method": "comparative_clip",
        "model_name": "RN50",
        "template": "a photo of a {class}, {comparative_descriptor}",
        "avg_descriptors_per_class": 19.2
    },
    "Caltech_256": {
        "accuracy_top1": 0.8068415721893685,
        "accuracy_top5": 0.9291992027967458,
        "num_classes": 257,
        "num_images": 30607,
        "method": "comparative_clip",
        "model_name": "RN50",
        "template": "a photo of a {class}, {comparative_descriptor}",
        "avg_descriptors_per_class": 19.700389105058367
    },
    "CompCars": {
        "accuracy_top1": 0.0015564355655377584,
        "accuracy_top5": 0.009121894517012431,
        "num_classes": 663,
        "num_images": 50757,
        "method": "comparative_clip",
        "model_name": "RN50",
        "template": "a photo of a {class}, {comparative_descriptor}",
        "avg_descriptors_per_class": 20.06184012066365
    },
    "CUB_200_2011": {
        "accuracy_top1": 0.4717700915564598,
        "accuracy_top5": 0.8143438453713123,
        "num_classes": 200,
        "num_images": 11796,
        "method": "comparative_clip",
        "model_name": "RN50",
        "template": "a photo of a {class}, {comparative_descriptor}",
        "avg_descriptors_per_class": 17.405
    },
    "DTD": {
        "accuracy_top1": 0.4299645390070922,
        "accuracy_top5": 0.7358156028368794,
        "num_classes": 47,
        "num_images": 5640,
        "method": "comparative_clip",
        "model_name": "RN50",
        "template": "a photo of a {class}, {comparative_descriptor}",
        "avg_descriptors_per_class": 20.74468085106383
    },
    "FGVC_Aircraft": {
        "accuracy_top1": 0.21902190219021903,
        "accuracy_top5": 0.5439543954395439,
        "num_classes": 70,
        "num_images": 3333,
        "method": "comparative_clip",
        "model_name": "RN50",
        "template": "a photo of a {class}, {comparative_descriptor}",
        "avg_descriptors_per_class": 20.228571428571428
    },
    "Flavia_Leaves": {
        "accuracy_top1": 0.11081932773109243,
        "accuracy_top5": 0.3088235294117647,
        "num_classes": 32,
        "num_images": 1904,
        "method": "comparative_clip",
        "model_name": "RN50",
        "template": "a photo of a {class}, {comparative_descriptor}",
        "avg_descriptors_per_class": 19.375
    },
    "food-101": {
        "accuracy_top1": 0.747039603960396,
        "accuracy_top5": 0.9335445544554456,
        "num_classes": 101,
        "num_images": 101000,
        "method": "comparative_clip",
        "model_name": "RN50",
        "template": "a photo of a {class}, {comparative_descriptor}",
        "avg_descriptors_per_class": 20.455445544554454
    },
    "FoodX-251": {
        "accuracy_top1": 0.5821243955310988,
        "accuracy_top5": 0.8389194597298649,
        "num_classes": 251,
        "num_images": 11994,
        "method": "comparative_clip",
        "model_name": "RN50",
        "template": "a photo of a {class}, {comparative_descriptor}",
        "avg_descriptors_per_class": 20.211155378486055
    },
    "Leaf": {
        "accuracy_top1": 0.23111646102919048,
        "accuracy_top5": 0.760758350887752,
        "num_classes": 10,
        "num_images": 3323,
        "method": "comparative_clip",
        "model_name": "RN50",
        "template": "a photo of a {class}, {comparative_descriptor}",
        "avg_descriptors_per_class": 18.7
    },
    "Leeds_Butterfly": {
        "accuracy_top1": 0.6911057692307693,
        "accuracy_top5": 0.90625,
        "num_classes": 10,
        "num_images": 832,
        "method": "comparative_clip",
        "model_name": "RN50",
        "template": "a photo of a {class}, {comparative_descriptor}",
        "avg_descriptors_per_class": 19.6
    },
    "LZUPSD": {
        "accuracy_top1": 0.00956405693950178,
        "accuracy_top5": 0.07451067615658363,
        "num_classes": 88,
        "num_images": 4496,
        "method": "comparative_clip",
        "model_name": "RN50",
        "template": "a photo of a {class}, {comparative_descriptor}",
        "avg_descriptors_per_class": 19.272727272727273
    },
    "MIT_Indoor_Scenes": {
        "accuracy_top1": 0.7423281440194759,
        "accuracy_top5": 0.9607277852520981,
        "num_classes": 67,
        "num_images": 15609,
        "method": "comparative_clip",
        "model_name": "RN50",
        "template": "a photo of a {class}, {comparative_descriptor}",
        "avg_descriptors_per_class": 20.91044776119403
    },
    "MNIST_Butterfly": {
        "accuracy_top1": 0.312,
        "accuracy_top5": 0.494,
        "num_classes": 100,
        "num_images": 500,
        "method": "comparative_clip",
        "model_name": "RN50",
        "template": "a photo of a {class}, {comparative_descriptor}",
        "avg_descriptors_per_class": 19.17
    },
    "NA_Fish": {
        "accuracy_top1": 0.536,
        "accuracy_top5": 0.9826666666666667,
        "num_classes": 9,
        "num_images": 9000,
        "method": "comparative_clip",
        "model_name": "RN50",
        "template": "a photo of a {class}, {comparative_descriptor}",
        "avg_descriptors_per_class": 16.333333333333332
    },
    "Oxford-IIIT_Pet_Dataset": {
        "accuracy_top1": 0.7919880904046556,
        "accuracy_top5": 0.9729327378535662,
        "num_classes": 37,
        "num_images": 7389,
        "method": "comparative_clip",
        "model_name": "RN50",
        "template": "a photo of a {class}, {comparative_descriptor}",
        "avg_descriptors_per_class": 17.945945945945947
    },
    "Oxford_Flowers_192": {
        "accuracy_top1": 0.6552567237163814,
        "accuracy_top5": 0.8484107579462102,
        "num_classes": 102,
        "num_images": 818,
        "method": "comparative_clip",
        "model_name": "RN50",
        "template": "a photo of a {class}, {comparative_descriptor}",
        "avg_descriptors_per_class": 18.558823529411764
    },
    "SlowSketch": {
        "accuracy_top1": 0.5569917743830788,
        "accuracy_top5": 0.8519388954171563,
        "num_classes": 20,
        "num_images": 1702,
        "method": "comparative_clip",
        "model_name": "RN50",
        "template": "a photo of a {class}, {comparative_descriptor}",
        "avg_descriptors_per_class": 19.25
    },
    "Stanford_Cars": {
        "accuracy_top1": 0.537205304518664,
        "accuracy_top5": 0.8860510805500982,
        "num_classes": 196,
        "num_images": 8144,
        "method": "comparative_clip",
        "model_name": "RN50",
        "template": "a photo of a {class}, {comparative_descriptor}",
        "avg_descriptors_per_class": 20.698979591836736
    },
    "Stanford_Dogs": {
        "accuracy_top1": 0.5425655976676385,
        "accuracy_top5": 0.8494169096209913,
        "num_classes": 120,
        "num_images": 20580,
        "method": "comparative_clip",
        "model_name": "RN50",
        "template": "a photo of a {class}, {comparative_descriptor}",
        "avg_descriptors_per_class": 17.391666666666666
    }
}