{
    "Black Sea Sprat": [
        "smaller size",
        "shorter tail",
        "slimmer body shape",
        "curved tail",
        "slimmer body",
        "fin shape distinct",
        "curved upper lip",
        "distinct black spots",
        "distinctive spots"
    ],
    "Gilt-Head Bream": [
        "distinct black lateral line",
        "distinct lateral line pattern",
        "slimmer body profile",
        "slightly larger size",
        "smaller size",
        "lighter belly",
        "sharper head angles",
        "rounded snout",
        "shorter, straighter snout"
    ],
    "Hourse Mackerel": [
        "distinctive dark spots",
        "distinctive blue stripe",
        "slimmer body shape",
        "slimmer body profile",
        "larger size",
        "distinct black stripe",
        "lighter belly color",
        "brighter belly color",
        "smaller size",
        "fin shape varies",
        "different color shades",
        "pointed snout",
        "shorter, straighter snout",
        "distinctively shaped tail fin",
        "darker belly"
    ],
    "Red Mullet": [
        "smaller size",
        "distinctive black spot",
        "slimmer body shape",
        "curved tail fin",
        "larger size",
        "thicker body",
        "brighter red color",
        "distinctive white stripes",
        "distinct black dots",
        "distinctive spots",
        "pointed snout"
    ],
    "Red Sea Bream": [
        "rounded head",
        "slimmer body",
        "larger size",
        "wider head",
        "rounder head",
        "distinct black spot",
        "Red Sea Bream has distinctive visual features",
        "brighter scales",
        "rounded snout"
    ],
    "Sea Bass": [
        "larger, forked tail",
        "distinctive dark stripe",
        "larger size",
        "smaller, rounder scales",
        "slimmer body shape",
        "smaller, upturned snout",
        "slimmer body",
        "distinctive scales pattern",
        "flat head",
        "lighter belly color",
        "shorter, straighter beak",
        "rounded head",
        "smaller fins",
        "distinct lateral line pattern",
        "distinctive greenish-blue scales"
    ],
    "Shrimp": [
        "lighter color",
        "pale color",
        "rounder shape",
        "round body",
        "thin legs",
        "rounder body",
        "smaller size",
        "curved tail",
        "antenna pair",
        "shorter antennae",
        "short antennae",
        "absence of fins",
        "pincer-like appendages",
        "fin shape different"
    ],
    "Striped Red Mullet": [
        "slimmer body shape",
        "fin shape differs",
        "redder body",
        "slimmer body",
        "slimmer shape",
        "larger size",
        "finer stripes pattern",
        "striped body",
        "striated body pattern",
        "curvier tail",
        "redder belly",
        "slimmer profile"
    ],
    "Trout": [
        "slimmer body shape",
        "shorter, straighter snout",
        "distinctively scaled skin",
        "smaller size",
        "distinctive lateral stripes",
        "smaller size than Sea Bass",
        "brighter scales color",
        "shorter, straighter beak",
        "brighter coloration",
        "greenish-blue scales",
        "pointier head"
    ]
}